Workbook

Sheet Raw_Data
A1: Order_ID | B1: Date | C1: Customer_Name | D1: City | E1: Medicine_Name | F1: Category | G1: Quantity | H1: Unit_Price | I1: Cost_Price | J1: Total_Sales | K1: Discount_% | L1: Final_Amount | M1: Payment_Mode | N1: Prescription
A2: ORD-0001 | B2: 45619 | C2: Swati Patel | D2: Chennai | E2: Paracetamol 500mg | F2: Tablet | G2: 8 | H2: 20 | I2: 10.4 | J2: 160 | K2: 5 | L2: 152 | M2: Cash | N2: Yes
A3: ORD-0002 | B3: 45594 | C3: Swati Singh | D3: Mumbai | E3: Omeprazole 20mg | F3: Capsule | G3: 3 | H3: 40 | I3: 20 | J3: 120 | K3: 5 | L3: 114 | M3: UPI | N3: Yes
A4: ORD-0003 | B4: 45624 | C4: Rahul Dubey | D4: Kolkata | E4: Soframycin Cream | F4: Cream | G4: 8 | H4: 72 | I4: 33.84 | J4: 576 | K4: 15 | L4: 489.6 | M4: UPI | N4: No
A5: ORD-0004 | B5: 45373 | C5: Sunita Patel | D5: Pune | E5: Candid Cream | F5: Cream | G5: 9 | H5: 65 | I5: 30.55 | J5: 585 | K5: 0 | L5: 585 | M5: UPI | N5: Yes
A6: ORD-0005 | B6: 45486 | C6: Swati Patel | D6: Pune | E6: Ibuprofen 400mg | F6: Tablet | G6: 20 | H6: 30 | I6: 15.6 | J6: 600 | K6: 5 | L6: 570 | M6: UPI | N6: No
A7: ORD-0006 | B7: 45485 | C7: Priya Agarwal | D7: Chennai | E7: Azithromycin 500mg | F7: Tablet | G7: 20 | H7: 150 | I7: 78 | J7: 3000 | K7: 10 | L7: 2700 | M7: UPI | N7: Yes
A8: ORD-0007 | B8: 45408 | C8: Meera Gupta | D8: Delhi | E8: Protein Supplement | F8: Powder | G8: 8 | H8: 450 | I8: 247.5 | J8: 3600 | K8: 0 | L8: 3600 | M8: Card | N8: No
A9: ORD-0008 | B9: 45481 | C9: Sanjay Mehta | D9: Chennai | E9: Ondansetron Inj | F9: Injection | G9: 3 | H9: 120 | I9: 72 | J9: 360 | K9: 0 | L9: 360 | M9: Cash | N9: Yes
A10: ORD-0009 | B10: 45430 | C10: Deepa Mishra | D10: Jaipur | E10: Soframycin Cream | F10: Cream | G10: 8 | H10: 72 | I10: 33.84 | J10: 576 | K10: 10 | L10: 518.4 | M10: UPI | N10: No
A11: ORD-0010 | B11: 45308 | C11: Arjun Singh | D11: Kolkata | E11: Protein Supplement | F11: Powder | G11: 9 | H11: 450 | I11: 247.5 | J11: 4050 | K11: 0 | L11: 4050 | M11: UPI | N11: No
A12: ORD-0011 | B12: 45627 | C12: Swati Kumar | D12: Ahmedabad | E12: Vitamin D3 60K | F12: Capsule | G12: 5 | H12: 55 | I12: 27.5 | J12: 275 | K12: 5 | L12: 261.25 | M12: UPI | N12: Yes
A13: ORD-0012 | B13: 45591 | C13: Priya Mishra | D13: Pune | E13: Vitamin D3 60K | F13: Capsule | G13: 8 | H13: 55 | I13: 27.5 | J13: 440 | K13: 0 | L13: 440 | M13: Cash | N13: Yes
... A501: ORD-0500 | B501: 45555 | C501: Sunita Agarwal | D501: Hyderabad | E501: Candid Cream | F501: Cream | G501: 5 | H501: 65 | I501: 30.55 | J501: 325 | K501: 0 | L501: 325 | M501: UPI | N501: Yes

Sheet Cleaned_Data
A1: Order_ID | B1: Date | C1: Month | D1: Year | E1: Customer_Name | F1: City | G1: Medicine_Name | H1: Category | I1: Quantity | J1: Unit_Price | K1: Cost_Price | L1: Total_Sales | M1: Discount_% | N1: Final_Amount | O1: Gross_Profit | P1: Profit_Margin_% | Q1: Payment_Mode | R1: Prescription
A2: =Raw_Data!A2 -> ORD-0001 | B2: =Raw_Data!B2 -> 45619 | C2: =TEXT(Raw_Data!B2,"MMM") -> Nov | D2: =YEAR(Raw_Data!B2) -> 2024 | E2: =Raw_Data!C2 -> Swati Patel | F2: =Raw_Data!D2 -> Chennai | G2: =Raw_Data!E2 -> Paracetamol 500mg | H2: =Raw_Data!F2 -> Tablet | I2: =Raw_Data!G2 -> 8 | J2: =Raw_Data!H2 -> 20 | K2: =Raw_Data!I2 -> 10.4 | L2: =Raw_Data!J2 -> 160 | ... N2: =Raw_Data!L2 -> 152 | O2: =L2-(I2*K2) -> 76.8 | P2: =IFERROR((L2-(I2*K2))/L2,0) -> 0.48 | Q2: =Raw_Data!M2 -> Cash | R2: =Raw_Data!N2 -> Yes
A3: =Raw_Data!A3 -> ORD-0002 | B3: =Raw_Data!B3 -> 45594 | C3: =TEXT(Raw_Data!B3,"MMM") -> Oct | D3: =YEAR(Raw_Data!B3) -> 2024 | E3: =Raw_Data!C3 -> Swati Singh | F3: =Raw_Data!D3 -> Mumbai | G3: =Raw_Data!E3 -> Omeprazole 20mg | H3: =Raw_Data!F3 -> Capsule | I3: =Raw_Data!G3 -> 3 | J3: =Raw_Data!H3 -> 40 | K3: =Raw_Data!I3 -> 20 | L3: =Raw_Data!J3 -> 120 | ... N3: =Raw_Data!L3 -> 114 | O3: =L3-(I3*K3) -> 60 | P3: =IFERROR((L3-(I3*K3))/L3,0) -> 0.5 | Q3: =Raw_Data!M3 -> UPI | R3: =Raw_Data!N3 -> Yes
A4: =Raw_Data!A4 -> ORD-0003 | B4: =Raw_Data!B4 -> 45624 | C4: =TEXT(Raw_Data!B4,"MMM") -> Nov | D4: =YEAR(Raw_Data!B4) -> 2024 | E4: =Raw_Data!C4 -> Rahul Dubey | F4: =Raw_Data!D4 -> Kolkata | G4: =Raw_Data!E4 -> Soframycin Cream | H4: =Raw_Data!F4 -> Cream | I4: =Raw_Data!G4 -> 8 | J4: =Raw_Data!H4 -> 72 | K4: =Raw_Data!I4 -> 33.84 | L4: =Raw_Data!J4 -> 576 | ... N4: =Raw_Data!L4 -> 489.6 | O4: =L4-(I4*K4) -> 305.28 | P4: =IFERROR((L4-(I4*K4))/L4,0) -> 0.53 | Q4: =Raw_Data!M4 -> UPI | R4: =Raw_Data!N4 -> No
A5: =Raw_Data!A5 -> ORD-0004 | B5: =Raw_Data!B5 -> 45373 | C5: =TEXT(Raw_Data!B5,"MMM") -> Mar | D5: =YEAR(Raw_Data!B5) -> 2024 | E5: =Raw_Data!C5 -> Sunita Patel | F5: =Raw_Data!D5 -> Pune | G5: =Raw_Data!E5 -> Candid Cream | H5: =Raw_Data!F5 -> Cream | I5: =Raw_Data!G5 -> 9 | J5: =Raw_Data!H5 -> 65 | K5: =Raw_Data!I5 -> 30.55 | L5: =Raw_Data!J5 -> 585 | ... N5: =Raw_Data!L5 -> 585 | O5: =L5-(I5*K5) -> 310.05 | P5: =IFERROR((L5-(I5*K5))/L5,0) -> 0.53 | Q5: =Raw_Data!M5 -> UPI | R5: =Raw_Data!N5 -> Yes
A6: =Raw_Data!A6 -> ORD-0005 | B6: =Raw_Data!B6 -> 45486 | C6: =TEXT(Raw_Data!B6,"MMM") -> Jul | D6: =YEAR(Raw_Data!B6) -> 2024 | E6: =Raw_Data!C6 -> Swati Patel | F6: =Raw_Data!D6 -> Pune | G6: =Raw_Data!E6 -> Ibuprofen 400mg | H6: =Raw_Data!F6 -> Tablet | I6: =Raw_Data!G6 -> 20 | J6: =Raw_Data!H6 -> 30 | K6: =Raw_Data!I6 -> 15.6 | L6: =Raw_Data!J6 -> 600 | ... N6: =Raw_Data!L6 -> 570 | O6: =L6-(I6*K6) -> 288 | P6: =IFERROR((L6-(I6*K6))/L6,0) -> 0.48 | Q6: =Raw_Data!M6 -> UPI | R6: =Raw_Data!N6 -> No
A7: =Raw_Data!A7 -> ORD-0006 | B7: =Raw_Data!B7 -> 45485 | C7: =TEXT(Raw_Data!B7,"MMM") -> Jul | D7: =YEAR(Raw_Data!B7) -> 2024 | E7: =Raw_Data!C7 -> Priya Agarwal | F7: =Raw_Data!D7 -> Chennai | G7: =Raw_Data!E7 -> Azithromycin 500mg | H7: =Raw_Data!F7 -> Tablet | I7: =Raw_Data!G7 -> 20 | J7: =Raw_Data!H7 -> 150 | K7: =Raw_Data!I7 -> 78 | L7: =Raw_Data!J7 -> 3000 | ... N7: =Raw_Data!L7 -> 2700 | O7: =L7-(I7*K7) -> 1440 | P7: =IFERROR((L7-(I7*K7))/L7,0) -> 0.48 | Q7: =Raw_Data!M7 -> UPI | R7: =Raw_Data!N7 -> Yes
A8: =Raw_Data!A8 -> ORD-0007 | B8: =Raw_Data!B8 -> 45408 | C8: =TEXT(Raw_Data!B8,"MMM") -> Apr | D8: =YEAR(Raw_Data!B8) -> 2024 | E8: =Raw_Data!C8 -> Meera Gupta | F8: =Raw_Data!D8 -> Delhi | G8: =Raw_Data!E8 -> Protein Supplement | H8: =Raw_Data!F8 -> Powder | I8: =Raw_Data!G8 -> 8 | J8: =Raw_Data!H8 -> 450 | K8: =Raw_Data!I8 -> 247.5 | L8: =Raw_Data!J8 -> 3600 | ... N8: =Raw_Data!L8 -> 3600 | O8: =L8-(I8*K8) -> 1620 | P8: =IFERROR((L8-(I8*K8))/L8,0) -> 0.45 | Q8: =Raw_Data!M8 -> Card | R8: =Raw_Data!N8 -> No
A9: =Raw_Data!A9 -> ORD-0008 | B9: =Raw_Data!B9 -> 45481 | C9: =TEXT(Raw_Data!B9,"MMM") -> Jul | D9: =YEAR(Raw_Data!B9) -> 2024 | E9: =Raw_Data!C9 -> Sanjay Mehta | F9: =Raw_Data!D9 -> Chennai | G9: =Raw_Data!E9 -> Ondansetron Inj | H9: =Raw_Data!F9 -> Injection | I9: =Raw_Data!G9 -> 3 | J9: =Raw_Data!H9 -> 120 | K9: =Raw_Data!I9 -> 72 | L9: =Raw_Data!J9 -> 360 | ... N9: =Raw_Data!L9 -> 360 | O9: =L9-(I9*K9) -> 144 | P9: =IFERROR((L9-(I9*K9))/L9,0) -> 0.4 | Q9: =Raw_Data!M9 -> Cash | R9: =Raw_Data!N9 -> Yes
A10: =Raw_Data!A10 -> ORD-0009 | B10: =Raw_Data!B10 -> 45430 | C10: =TEXT(Raw_Data!B10,"MMM") -> May | D10: =YEAR(Raw_Data!B10) -> 2024 | E10: =Raw_Data!C10 -> Deepa Mishra | F10: =Raw_Data!D10 -> Jaipur | G10: =Raw_Data!E10 -> Soframycin Cream | H10: =Raw_Data!F10 -> Cream | I10: =Raw_Data!G10 -> 8 | J10: =Raw_Data!H10 -> 72 | K10: =Raw_Data!I10 -> 33.84 | L10: =Raw_Data!J10 -> 576 | ... N10: =Raw_Data!L10 -> 518.4 | O10: =L10-(I10*K10) -> 305.28 | P10: =IFERROR((L10-(I10*K10))/L10,0) -> 0.53 | Q10: =Raw_Data!M10 -> UPI | R10: =Raw_Data!N10 -> No
A11: =Raw_Data!A11 -> ORD-0010 | B11: =Raw_Data!B11 -> 45308 | C11: =TEXT(Raw_Data!B11,"MMM") -> Jan | D11: =YEAR(Raw_Data!B11) -> 2024 | E11: =Raw_Data!C11 -> Arjun Singh | F11: =Raw_Data!D11 -> Kolkata | G11: =Raw_Data!E11 -> Protein Supplement | H11: =Raw_Data!F11 -> Powder | I11: =Raw_Data!G11 -> 9 | J11: =Raw_Data!H11 -> 450 | K11: =Raw_Data!I11 -> 247.5 | L11: =Raw_Data!J11 -> 4050 | ... N11: =Raw_Data!L11 -> 4050 | O11: =L11-(I11*K11) -> 1822.5 | P11: =IFERROR((L11-(I11*K11))/L11,0) -> 0.45 | Q11: =Raw_Data!M11 -> UPI | R11: =Raw_Data!N11 -> No
A12: =Raw_Data!A12 -> ORD-0011 | B12: =Raw_Data!B12 -> 45627 | C12: =TEXT(Raw_Data!B12,"MMM") -> Dec | D12: =YEAR(Raw_Data!B12) -> 2024 | E12: =Raw_Data!C12 -> Swati Kumar | F12: =Raw_Data!D12 -> Ahmedabad | G12: =Raw_Data!E12 -> Vitamin D3 60K | H12: =Raw_Data!F12 -> Capsule | I12: =Raw_Data!G12 -> 5 | J12: =Raw_Data!H12 -> 55 | K12: =Raw_Data!I12 -> 27.5 | L12: =Raw_Data!J12 -> 275 | ... N12: =Raw_Data!L12 -> 261.25 | O12: =L12-(I12*K12) -> 137.5 | P12: =IFERROR((L12-(I12*K12))/L12,0) -> 0.5 | Q12: =Raw_Data!M12 -> UPI | R12: =Raw_Data!N12 -> Yes
A13: =Raw_Data!A13 -> ORD-0012 | B13: =Raw_Data!B13 -> 45591 | C13: =TEXT(Raw_Data!B13,"MMM") -> Oct | D13: =YEAR(Raw_Data!B13) -> 2024 | E13: =Raw_Data!C13 -> Priya Mishra | F13: =Raw_Data!D13 -> Pune | G13: =Raw_Data!E13 -> Vitamin D3 60K | H13: =Raw_Data!F13 -> Capsule | I13: =Raw_Data!G13 -> 8 | J13: =Raw_Data!H13 -> 55 | K13: =Raw_Data!I13 -> 27.5 | L13: =Raw_Data!J13 -> 440 | ... N13: =Raw_Data!L13 -> 440 | O13: =L13-(I13*K13) -> 220 | P13: =IFERROR((L13-(I13*K13))/L13,0) -> 0.5 | Q13: =Raw_Data!M13 -> Cash | R13: =Raw_Data!N13 -> Yes
... A501: =Raw_Data!A501 -> ORD-0500 | B501: =Raw_Data!B501 -> 45555 | C501: =TEXT(Raw_Data!B501,"MMM") -> Sep | D501: =YEAR(Raw_Data!B501) -> 2024 | E501: =Raw_Data!C501 -> Sunita Agarwal | F501: =Raw_Data!D501 -> Hyderabad | G501: =Raw_Data!E501 -> Candid Cream | H501: =Raw_Data!F501 -> Cream | I501: =Raw_Data!G501 -> 5 | J501: =Raw_Data!H501 -> 65 | K501: =Raw_Data!I501 -> 30.55 | L501: =Raw_Data!J501 -> 325 | ... N501: =Raw_Data!L501 -> 325 | O501: =L501-(I501*K501) -> 172.25 | P501: =IFERROR((L501-(I501*K501))/L501,0) -> 0.53 | Q501: =Raw_Data!M501 -> UPI | R501: =Raw_Data!N501 -> Yes

Sheet Summary_KPIs
A1: 💊 PHARMACY SALES DASHBOARD — SUMMARY & KPIs (2024)
A3: KEY METRICS | B3: 💰 Total Sales (₹) | D3: 📦 Total Orders | F3: 💊 Total Qty Sold | H3: 🧾 Avg Order Value (₹) | J3: 📉 Total Discount Given | L3: ✅ Avg Profit Margin
B4: =SUM(Cleaned_Data!L2:L501) -> 630358 | D4: =COUNTA(Cleaned_Data!A2:A501) -> 500 | F4: =SUM(Cleaned_Data!I2:I501) -> 5305 | H4: =IFERROR(B4/D4,0) -> 1260.716 | J4: =SUMPRODUCT(Cleaned_Data!J2:J501,Cleaned_Data!M2:M501/100) -> 4408.4 | L4: =AVERAGEIF(Cleaned_Data!P2:P501,">0") -> 0.48708
A7: SALES BY CATEGORY | G7: MONTHLY SALES TREND | K7: PAYMENT MODE SPLIT
A8: Category | B8: Total Sales (₹) | C8: Total Orders | D8: Avg Order (₹) | E8: Qty Sold | G8: Month | H8: Total Sales (₹) | I8: Orders | K8: Payment Mode | L8: Total Sales (₹) | M8: % Share
A9: Capsule | B9: =SUMIF(Cleaned_Data!H2:H501,A9,Cleaned_Data!L2:L501) -> 39715 | C9: =COUNTIF(Cleaned_Data!H2:H501,A9) -> 67 | D9: =IFERROR(B9/C9,0) -> 592.76119 | E9: =SUMIF(Cleaned_Data!H2:H501,A9,Cleaned_Data!I2:I501) -> 660 | G9: Jan | H9: =SUMIF(Cleaned_Data!C2:C501,G9,Cleaned_Data!L2:L501) -> 60563 | I9: =COUNTIF(Cleaned_Data!C2:C501,G9) -> 44 | K9: Cash | L9: =SUMIF(Cleaned_Data!Q2:Q501,K9,Cleaned_Data!L2:L501) -> 180818 | M9: =IFERROR(L9/SUM(L9:L11),0) -> 0.28684969
A10: Cream | B10: =SUMIF(Cleaned_Data!H2:H501,A10,Cleaned_Data!L2:L501) -> 56799 | C10: =COUNTIF(Cleaned_Data!H2:H501,A10) -> 68 | D10: =IFERROR(B10/C10,0) -> 835.27941 | E10: =SUMIF(Cleaned_Data!H2:H501,A10,Cleaned_Data!I2:I501) -> 770 | G10: Feb | H10: =SUMIF(Cleaned_Data!C2:C501,G10,Cleaned_Data!L2:L501) -> 49168 | I10: =COUNTIF(Cleaned_Data!C2:C501,G10) -> 41 | K10: Card | L10: =SUMIF(Cleaned_Data!Q2:Q501,K10,Cleaned_Data!L2:L501) -> 193139 | M10: =IFERROR(L10/SUM(L9:L11),0) -> 0.30639573
A11: Drops | B11: =SUMIF(Cleaned_Data!H2:H501,A11,Cleaned_Data!L2:L501) -> 71460 | C11: =COUNTIF(Cleaned_Data!H2:H501,A11) -> 68 | D11: =IFERROR(B11/C11,0) -> 1050.8824 | E11: =SUMIF(Cleaned_Data!H2:H501,A11,Cleaned_Data!I2:I501) -> 787 | G11: Mar | H11: =SUMIF(Cleaned_Data!C2:C501,G11,Cleaned_Data!L2:L501) -> 54725 | I11: =COUNTIF(Cleaned_Data!C2:C501,G11) -> 46 | K11: UPI | L11: =SUMIF(Cleaned_Data!Q2:Q501,K11,Cleaned_Data!L2:L501) -> 256401 | M11: =IFERROR(L11/SUM(L9:L11),0) -> 0.40675457
A12: Injection | B12: =SUMIF(Cleaned_Data!H2:H501,A12,Cleaned_Data!L2:L501) -> 184555 | C12: =COUNTIF(Cleaned_Data!H2:H501,A12) -> 75 | D12: =IFERROR(B12/C12,0) -> 2460.7333 | E12: =SUMIF(Cleaned_Data!H2:H501,A12,Cleaned_Data!I2:I501) -> 792 | G12: Apr | H12: =SUMIF(Cleaned_Data!C2:C501,G12,Cleaned_Data!L2:L501) -> 28326 | I12: =COUNTIF(Cleaned_Data!C2:C501,G12) -> 24
A13: Powder | B13: =SUMIF(Cleaned_Data!H2:H501,A13,Cleaned_Data!L2:L501) -> 178125 | C13: =COUNTIF(Cleaned_Data!H2:H501,A13) -> 84 | D13: =IFERROR(B13/C13,0) -> 2120.5357 | E13: =SUMIF(Cleaned_Data!H2:H501,A13,Cleaned_Data!I2:I501) -> 865 | G13: May | H13: =SUMIF(Cleaned_Data!C2:C501,G13,Cleaned_Data!L2:L501) -> 20021 | I13: =COUNTIF(Cleaned_Data!C2:C501,G13) -> 18
A14: Syrup | B14: =SUMIF(Cleaned_Data!H2:H501,A14,Cleaned_Data!L2:L501) -> 45535 | C14: =COUNTIF(Cleaned_Data!H2:H501,A14) -> 64 | D14: =IFERROR(B14/C14,0) -> 711.48438 | E14: =SUMIF(Cleaned_Data!H2:H501,A14,Cleaned_Data!I2:I501) -> 667 | G14: Jun | H14: =SUMIF(Cleaned_Data!C2:C501,G14,Cleaned_Data!L2:L501) -> 37795 | I14: =COUNTIF(Cleaned_Data!C2:C501,G14) -> 33
A15: Tablet | B15: =SUMIF(Cleaned_Data!H2:H501,A15,Cleaned_Data!L2:L501) -> 54169 | C15: =COUNTIF(Cleaned_Data!H2:H501,A15) -> 74 | D15: =IFERROR(B15/C15,0) -> 732.01351 | E15: =SUMIF(Cleaned_Data!H2:H501,A15,Cleaned_Data!I2:I501) -> 764 | G15: Jul | H15: =SUMIF(Cleaned_Data!C2:C501,G15,Cleaned_Data!L2:L501) -> 57718 | I15: =COUNTIF(Cleaned_Data!C2:C501,G15) -> 42
G16: Aug | H16: =SUMIF(Cleaned_Data!C2:C501,G16,Cleaned_Data!L2:L501) -> 52560 | I16: =COUNTIF(Cleaned_Data!C2:C501,G16) -> 47
G17: Sep | H17: =SUMIF(Cleaned_Data!C2:C501,G17,Cleaned_Data!L2:L501) -> 100773 | I17: =COUNTIF(Cleaned_Data!C2:C501,G17) -> 51
G18: Oct | H18: =SUMIF(Cleaned_Data!C2:C501,G18,Cleaned_Data!L2:L501) -> 70516 | I18: =COUNTIF(Cleaned_Data!C2:C501,G18) -> 52
G19: Nov | H19: =SUMIF(Cleaned_Data!C2:C501,G19,Cleaned_Data!L2:L501) -> 56810 | I19: =COUNTIF(Cleaned_Data!C2:C501,G19) -> 53
G20: Dec | H20: =SUMIF(Cleaned_Data!C2:C501,G20,Cleaned_Data!L2:L501) -> 41383 | I20: =COUNTIF(Cleaned_Data!C2:C501,G20) -> 49
A22: CITY-WISE SALES PERFORMANCE | G22: PRESCRIPTION vs NON-PRESCRIPTION
A23: City | B23: Total Sales (₹) | C23: Total Orders | D23: Qty Sold | E23: Avg Order (₹) | G23: Type | H23: Total Sales (₹) | I23: % Share
A24: Ahmedabad | B24: =SUMIF(Cleaned_Data!F2:F501,A24,Cleaned_Data!L2:L501) -> 41581 | C24: =COUNTIF(Cleaned_Data!F2:F501,A24) -> 43 | D24: =SUMIF(Cleaned_Data!F2:F501,A24,Cleaned_Data!I2:I501) -> 458 | E24: =IFERROR(B24/C24,0) -> 967 | G24: Prescription | H24: =SUMIF(Cleaned_Data!R2:R501,"Yes",Cleaned_Data!L2:L501) -> 305004 | I24: =IFERROR(H24/SUM(H24:H25),0) -> 0.48385838
A25: Bangalore | B25: =SUMIF(Cleaned_Data!F2:F501,A25,Cleaned_Data!L2:L501) -> 63933 | C25: =COUNTIF(Cleaned_Data!F2:F501,A25) -> 61 | D25: =SUMIF(Cleaned_Data!F2:F501,A25,Cleaned_Data!I2:I501) -> 610 | E25: =IFERROR(B25/C25,0) -> 1048.082 | G25: Non-Prescription | H25: =SUMIF(Cleaned_Data!R2:R501,"No",Cleaned_Data!L2:L501) -> 325354 | I25: =IFERROR(H25/SUM(H24:H25),0) -> 0.51614162
A26: Chennai | B26: =SUMIF(Cleaned_Data!F2:F501,A26,Cleaned_Data!L2:L501) -> 76517 | C26: =COUNTIF(Cleaned_Data!F2:F501,A26) -> 51 | D26: =SUMIF(Cleaned_Data!F2:F501,A26,Cleaned_Data!I2:I501) -> 642 | E26: =IFERROR(B26/C26,0) -> 1500.3333
A27: Delhi | B27: =SUMIF(Cleaned_Data!F2:F501,A27,Cleaned_Data!L2:L501) -> 63651 | C27: =COUNTIF(Cleaned_Data!F2:F501,A27) -> 55 | D27: =SUMIF(Cleaned_Data!F2:F501,A27,Cleaned_Data!I2:I501) -> 503 | E27: =IFERROR(B27/C27,0) -> 1157.2909
A28: Hyderabad | B28: =SUMIF(Cleaned_Data!F2:F501,A28,Cleaned_Data!L2:L501) -> 71697 | C28: =COUNTIF(Cleaned_Data!F2:F501,A28) -> 49 | D28: =SUMIF(Cleaned_Data!F2:F501,A28,Cleaned_Data!I2:I501) -> 482 | E28: =IFERROR(B28/C28,0) -> 1463.2041
A29: Jaipur | B29: =SUMIF(Cleaned_Data!F2:F501,A29,Cleaned_Data!L2:L501) -> 67715 | C29: =COUNTIF(Cleaned_Data!F2:F501,A29) -> 51 | D29: =SUMIF(Cleaned_Data!F2:F501,A29,Cleaned_Data!I2:I501) -> 584 | E29: =IFERROR(B29/C29,0) -> 1327.7451
A30: Kolkata | B30: =SUMIF(Cleaned_Data!F2:F501,A30,Cleaned_Data!L2:L501) -> 69570 | C30: =COUNTIF(Cleaned_Data!F2:F501,A30) -> 49 | D30: =SUMIF(Cleaned_Data!F2:F501,A30,Cleaned_Data!I2:I501) -> 577 | E30: =IFERROR(B30/C30,0) -> 1419.7959
A31: Mumbai | B31: =SUMIF(Cleaned_Data!F2:F501,A31,Cleaned_Data!L2:L501) -> 55071 | C31: =COUNTIF(Cleaned_Data!F2:F501,A31) -> 52 | D31: =SUMIF(Cleaned_Data!F2:F501,A31,Cleaned_Data!I2:I501) -> 495 | E31: =IFERROR(B31/C31,0) -> 1059.0577
A32: Pune | B32: =SUMIF(Cleaned_Data!F2:F501,A32,Cleaned_Data!L2:L501) -> 55535 | C32: =COUNTIF(Cleaned_Data!F2:F501,A32) -> 44 | D32: =SUMIF(Cleaned_Data!F2:F501,A32,Cleaned_Data!I2:I501) -> 435 | E32: =IFERROR(B32/C32,0) -> 1262.1591
A33: Surat | B33: =SUMIF(Cleaned_Data!F2:F501,A33,Cleaned_Data!L2:L501) -> 65088 | C33: =COUNTIF(Cleaned_Data!F2:F501,A33) -> 45 | D33: =SUMIF(Cleaned_Data!F2:F501,A33,Cleaned_Data!I2:I501) -> 519 | E33: =IFERROR(B33/C33,0) -> 1446.4
